brainglobe_heatmap/__init__.py
brainglobe_heatmap/heatmaps.py
brainglobe_heatmap/plane.py
brainglobe_heatmap/planner.py
brainglobe_heatmap/slicer.py
brainglobe_heatmap-0.6.0.dist-info/licenses/LICENSE
brainglobe_heatmap-0.6.0.dist-info/METADATA
brainglobe_heatmap-0.6.0.dist-info/WHEEL
brainglobe_heatmap-0.6.0.dist-info/top_level.txt
brainglobe_heatmap-0.6.0.dist-info/RECORD
