Metadata-Version: 2.4
Name: brainglobe-heatmap
Version: 0.6.0
Summary: Rendering anatomical heatmaps with brainrender and matplotlib
Author-email: Federico Claudi <hello@brainglobe.info>
License: MIT
Project-URL: Homepage, https://github.com/brainglobe/brainglobe-heatmap
Project-URL: Bug Tracker, https://github.com/brainglobe/brainglobe-heatmap/issues
Project-URL: Documentation, https://github.com/brainglobe/brainglobe-heatmap
Project-URL: Source Code, https://github.com/brainglobe/brainglobe-heatmap
Project-URL: User Support, https://github.com/brainglobe/brainglobe-heatmap/issues
Classifier: Development Status :: 2 - Pre-Alpha
Classifier: Programming Language :: Python
Classifier: Programming Language :: Python :: 3
Classifier: Programming Language :: Python :: 3.11
Classifier: Programming Language :: Python :: 3.12
Classifier: Programming Language :: Python :: 3.13
Classifier: Operating System :: OS Independent
Classifier: License :: OSI Approved :: MIT License
Requires-Python: >=3.11
License-File: LICENSE
Requires-Dist: brainrender>=2.1.17
Requires-Dist: matplotlib
Requires-Dist: numpy
Requires-Dist: myterial
Requires-Dist: rich
Requires-Dist: shapely
Provides-Extra: dev
Requires-Dist: pytest; extra == "dev"
Requires-Dist: pytest-cov; extra == "dev"
Requires-Dist: coverage; extra == "dev"
Requires-Dist: tox; extra == "dev"
Requires-Dist: black; extra == "dev"
Requires-Dist: mypy; extra == "dev"
Requires-Dist: pre-commit; extra == "dev"
Requires-Dist: ruff; extra == "dev"
Requires-Dist: setuptools_scm; extra == "dev"
Dynamic: license-file
